mipdb/__init__.py
mipdb/commands.py
mipdb/credentials.py
mipdb/data_frame.py
mipdb/data_frame_schema.py
mipdb/dataelements.py
mipdb/exceptions.py
mipdb/logger.py
mipdb/monetdb/__init__.py
mipdb/monetdb/monetdb.py
mipdb/monetdb/monetdb_tables.py
mipdb/monetdb/schema.py
mipdb/properties.py
mipdb/reader.py
mipdb/sqlite/__init__.py
mipdb/sqlite/sqlite.py
mipdb/sqlite/sqlite_tables.py
mipdb/usecases.py
mipdb-4.0.2.dist-info/METADATA
mipdb-4.0.2.dist-info/WHEEL
mipdb-4.0.2.dist-info/entry_points.txt
mipdb-4.0.2.dist-info/RECORD
