Metadata-Version: 2.1
Name: mipdb
Version: 4.0.2
Summary: 
Author: Your Name
Author-email: you@example.com
Requires-Python: >=3.10,<3.11
Classifier: Programming Language :: Python :: 3
Classifier: Programming Language :: Python :: 3.10
Requires-Dist: SQLAlchemy (>=2.0,<2.1)
Requires-Dist: click (>=8.1,<8.2)
Requires-Dist: numpy (>=2.2,<2.3)
Requires-Dist: pandas (>=2.3,<2.4)
Requires-Dist: pandera (>=0.25,<0.26)
Requires-Dist: pymonetdb (>=1.8,<1.9)
Requires-Dist: setuptools (>=80.9,<80.10)
Requires-Dist: sqlalchemy_monetdb (>=2.0,<2.1)
Requires-Dist: toml (>=0.10,<0.11)
